README.txt
setup.py
DeckenMagicPlugin.egg-info/PKG-INFO
DeckenMagicPlugin.egg-info/SOURCES.txt
DeckenMagicPlugin.egg-info/dependency_links.txt
DeckenMagicPlugin.egg-info/entry_points.txt
DeckenMagicPlugin.egg-info/requires.txt
DeckenMagicPlugin.egg-info/top_level.txt
deckenmagicplugin/__init__.py
deckenmagicplugin/conjunto.py
deckenmagicplugin/magicplugin.py