Metadata-Version: 1.0
Name: DeckenMagicPlugin
Version: 0.1.5
Summary: Decken Plugin to Trade Card Game Magic: the Gathering
Home-page: UNKNOWN
Author: Claudio Torcato
Author-email: claudiotorcato@gmail.com
License: PSF
Keywords: tcg mtg magic deck card python gnome linux mac n800
Platform: UNKNOWN
